{
  "(71\u201379": {
    "https://en.wikipedia.org/wiki/African_fish_eagle": [
      445
    ]
  },
  "(79": {
    "https://en.wikipedia.org/wiki/African_fish_eagle": [
      482
    ]
  },
  "(7\u20138)": {
    "https://en.wikipedia.org/wiki/African_fish_eagle": [
      1557
    ]
  },
  "70": {
    "https://en.wikipedia.org/wiki/African_fish_eagle": [
      976
    ]
  },
  "7021": {
    "https://en.wikipedia.org/wiki/African_fish_eagle": [
      1584
    ]
  },
  "75": {
    "https://en.wikipedia.org/wiki/African_fish_eagle": [
      978
    ]
  },
  "7675": {
    "https://en.wikipedia.org/wiki/African_fish_eagle": [
      1585
    ]
  },
  "783\u2013791": {
    "https://en.wikipedia.org/wiki/African_fish_eagle": [
      1558
    ]
  },
  "7895": {
    "https://en.wikipedia.org/wiki/African_fish_eagle": [
      2070
    ]
  },
  "7gallery": {
    "https://en.wikipedia.org/wiki/African_fish_eagle": [
      85
    ]
  }
}