{
  "(podica": {
    "https://en.wikipedia.org/wiki/African_finfoot": [
      182
    ]
  },
  "p": {
    "https://en.wikipedia.org/wiki/African_finfoot": [
      167
    ]
  },
  "page": {
    "https://en.wikipedia.org/wiki/African_finfoot": [
      37,
      53,
      748
    ]
  },
  "pagecontentscurrent": {
    "https://en.wikipedia.org/wiki/African_finfoot": [
      16
    ]
  },
  "pagespermanent": {
    "https://en.wikipedia.org/wiki/African_finfoot": [
      117
    ]
  },
  "pagewikidata": {
    "https://en.wikipedia.org/wiki/African_finfoot": [
      121
    ]
  },
  "pair": {
    "https://en.wikipedia.org/wiki/African_finfoot": [
      371
    ]
  },
  "pale": {
    "https://en.wikipedia.org/wiki/African_finfoot": [
      237
    ]
  },
  "pdfprintable": {
    "https://en.wikipedia.org/wiki/African_finfoot": [
      126
    ]
  },
  "persecute": {
    "https://en.wikipedia.org/wiki/African_finfoot": [
      529
    ]
  },
  "personal": {
    "https://en.wikipedia.org/wiki/African_finfoot": [
      47
    ]
  },
  "phylum": {
    "https://en.wikipedia.org/wiki/African_finfoot": [
      155
    ]
  },
  "pierre": {
    "https://en.wikipedia.org/wiki/African_finfoot": [
      729
    ]
  },
  "plumage": {
    "https://en.wikipedia.org/wiki/African_finfoot": [
      232
    ]
  },
  "podica": {
    "https://en.wikipedia.org/wiki/African_finfoot": [
      171,
      597,
      642,
      662,
      665,
      683,
      699
    ]
  },
  "podicalesson": {
    "https://en.wikipedia.org/wiki/African_finfoot": [
      164
    ]
  },
  "policy": {
    "https://en.wikipedia.org/wiki/African_finfoot": [
      788,
      804
    ]
  },
  "pollute": {
    "https://en.wikipedia.org/wiki/African_finfoot": [
      558
    ]
  },
  "poorly": {
    "https://en.wikipedia.org/wiki/African_finfoot": [
      502
    ]
  },
  "portalrecent": {
    "https://en.wikipedia.org/wiki/African_finfoot": [
      25
    ]
  },
  "prey": {
    "https://en.wikipedia.org/wiki/African_finfoot": [
      333
    ]
  },
  "print/export": {
    "https://en.wikipedia.org/wiki/African_finfoot": [
      123
    ]
  },
  "privacy": {
    "https://en.wikipedia.org/wiki/African_finfoot": [
      787,
      803
    ]
  },
  "prize": {
    "https://en.wikipedia.org/wiki/African_finfoot": [
      386
    ]
  },
  "profit": {
    "https://en.wikipedia.org/wiki/African_finfoot": [
      801
    ]
  },
  "project": {
    "https://en.wikipedia.org/wiki/African_finfoot": [
      130
    ]
  }
}