{
  "(iucn": {
    "https://en.wikipedia.org/wiki/Abdim%27s_stork": [
      153
    ]
  },
  "ibis)": {
    "https://en.wikipedia.org/wiki/Abdim%27s_stork": [
      680
    ]
  },
  "identify": {
    "https://en.wikipedia.org/wiki/Abdim%27s_stork": [
      770
    ]
  },
  "in": {
    "https://en.wikipedia.org/wiki/Abdim%27s_stork": [
      46,
      52,
      129,
      220,
      223,
      228,
      240,
      255,
      281,
      286,
      292,
      394,
      413,
      447,
      458,
      766,
      834
    ]
  },
  "in)": {
    "https://en.wikipedia.org/wiki/Abdim%27s_stork": [
      472
    ]
  },
  "inaturalist": {
    "https://en.wikipedia.org/wiki/Abdim%27s_stork": [
      799
    ]
  },
  "inc": {
    "https://en.wikipedia.org/wiki/Abdim%27s_stork": [
      904
    ]
  },
  "information": {
    "https://en.wikipedia.org/wiki/Abdim%27s_stork": [
      615
    ]
  },
  "informationcite": {
    "https://en.wikipedia.org/wiki/Abdim%27s_stork": [
      120
    ]
  },
  "insect": {
    "https://en.wikipedia.org/wiki/Abdim%27s_stork": [
      215,
      497
    ]
  },
  "insectivorous": {
    "https://en.wikipedia.org/wiki/Abdim%27s_stork": [
      489
    ]
  },
  "international": {
    "https://en.wikipedia.org/wiki/Abdim%27s_stork": [
      552,
      642
    ]
  },
  "into": {
    "https://en.wikipedia.org/wiki/Abdim%27s_stork": [
      331
    ]
  },
  "irmng": {
    "https://en.wikipedia.org/wiki/Abdim%27s_stork": [
      801
    ]
  },
  "is": {
    "https://en.wikipedia.org/wiki/Abdim%27s_stork": [
      197,
      206,
      217,
      252,
      336,
      342,
      371,
      385,
      403,
      426,
      462,
      487,
      519,
      867,
      896
    ]
  },
  "it": {
    "https://en.wikipedia.org/wiki/Abdim%27s_stork": [
      205,
      283,
      384,
      442,
      461
    ]
  },
  "item": {
    "https://en.wikipedia.org/wiki/Abdim%27s_stork": [
      123
    ]
  },
  "iti": {
    "https://en.wikipedia.org/wiki/Abdim%27s_stork": [
      803
    ]
  },
  "its": {
    "https://en.wikipedia.org/wiki/Abdim%27s_stork": [
      297,
      366
    ]
  },
  "iucn": {
    "https://en.wikipedia.org/wiki/Abdim%27s_stork": [
      378,
      556,
      805,
      819
    ]
  }
}